{
  "intro": "経験を積んだあなたが、JQITで次のステージへ進む道筋です。現場が違っても会社とつながり、推奨技術の習得を支援する。リーダー・専門性の深化、その先の受託・自社AIまで——あなたの経験を起点に、キャリアの幅を広げられます。",
  "steps": [
    {
      "no": "STEP 01",
      "title": "入社・立ち上がり",
      "period": "〜3か月 ※目安",
      "desc": "参画先の体制にかかわらず、営業・上長・事業部とつながりながら立ち上がります。これまでの経験を踏まえつつ、JQITの推奨技術や進め方をキャッチアップする時期です。",
      "support": "現場で孤立させない立ち上がり支援"
    },
    {
      "no": "STEP 02",
      "title": "戦力化／チームで発揮",
      "period": "〜1年 ※目安",
      "desc": "案件の中でこれまでの経験を戦力として発揮します。チーム参画の機会も活かしながら、推奨技術の習得には受験費用の全額支援とスペシャルテクニカルボーナスが効きます。リーダーを任される人も。",
      "support": "推奨技術の習得支援・資格費用 全額"
    },
    {
      "no": "STEP 03",
      "title": "リーダー／専門性の確立",
      "period": "2〜3年 ※目安",
      "desc": "自社メンバーを率いて現場をリードし、得意領域の専門性を深めます。上位資格にも挑戦でき、学んだ分は合格時の一時報奨金と月々の資格手当（最大6万円）で返ります。AI駆動開発を現場に持ち込む役割も。",
      "support": "上位資格支援・資格手当（最大6万円）"
    },
    {
      "no": "STEP 04",
      "title": "スペシャリスト／マネジメント、その先へ",
      "period": "その先へ",
      "desc": "高度専門職として技術を究めるか、チームを率いるマネージャーへ。さらにその先には、受託・自社AI（NOVA）プロダクトへ進む道もあります。年齢ではなく実力で評価されます。",
      "support": "実力評価が給与・ポジションに直結／受託・自社への道"
    }
  ],
  "closing": "学び続ける経験者を、JQITは全力で後押しします。推奨技術の習得支援と、資格の受験費用は全額負担。あなたの経験を、次のステージへ。"
}
